{
  "user": {
    "name": "Your Name",
    "company": "Alpaca Factory, LLC",
    "address": {
      "street": "999 Boulevard Ct.",
      "city": "Citytown",
      "state": "NJ",
      "zip": "54637"
    }
  },
  "projects": {},
  "clients": {},
  "sync": {
    "autoSync": false,
    "services": []
  },
  "invoice": {
    "dateFormat": "MM/DD/YYYY",
    "timeFormat": "h:mm A"
  },
  "display": {
    "dateFormat": "dddd, MMMM Do YYYY",
    "timeFormat": "h:mm A",
    "textColors": true,
    "wordWrapWidth": 65,
    "showPunchIDs": false,
    "showCommentIndices": false,
    "showDayGraphics": false
  },
  "storageType": "ledger"
}